__init__.py
setup.py
telneter.py
telneter.egg-info/PKG-INFO
telneter.egg-info/SOURCES.txt
telneter.egg-info/dependency_links.txt
telneter.egg-info/top_level.txt