Metadata-Version: 1.1
Name: telneter
Version: 0.0.8
Summary: Telnet interface for popular network devices: JUNOS, EXOS, IOS
Home-page: https://github.com/Pavel-Polyakov/telneter
Author: Pavel Polyakov
Author-email: polyakov.pavel.xyz@gmail.com
License: MIT License
Download-URL: https://github.com/Pavel-Polyakov/telneter/archive/master
Keywords: telnet
Platform: UNKNOWN
Classifier: Intended Audience :: Developers
Classifier: Programming Language :: Python
